{
  "inputs": {
    "scan.ts": {
      "bytes": 227807,
      "imports": [
        {
          "path": "util",
          "kind": "import-statement",
          "original": "node:util",
          "external": true
        },
        {
          "path": "fs/promises",
          "kind": "import-statement",
          "original": "node:fs/promises",
          "external": true
        },
        {
          "path": "os",
          "kind": "import-statement",
          "original": "node:os",
          "external": true
        },
        {
          "path": "crypto",
          "kind": "import-statement",
          "original": "node:crypto",
          "external": true
        },
        {
          "path": "bun",
          "kind": "import-statement",
          "external": true
        },
        {
          "path": "/Users/nolarose/Projects/scanner/node_modules/zod/index.js",
          "kind": "import-statement",
          "original": "zod"
        },
        {
          "path": "/Users/nolarose/Projects/scanner/src/scan-columns.ts",
          "kind": "import-statement",
          "original": "./src/scan-columns"
        },
        {
          "path": "/Users/nolarose/Projects/scanner/cli/renderers/status-glyphs.ts",
          "kind": "import-statement",
          "original": "./cli/renderers/status-glyphs"
        }
      ],
      "format": "esm"
    },
    "src/scan-columns.ts": {
      "bytes": 5599,
      "imports": [
      ],
      "format": "esm"
    },
    "node_modules/zod/index.js": {
      "bytes": 121,
      "imports": [
        {
          "path": "/Users/nolarose/Projects/scanner/node_modules/zod/v4/classic/external.js",
          "kind": "import-statement",
          "original": "./v4/classic/external.js"
        },
        {
          "path": "/Users/nolarose/Projects/scanner/node_modules/zod/v4/classic/external.js",
          "kind": "import-statement",
          "original": "./v4/classic/external.js"
        }
      ],
      "format": "esm"
    },
    "cli/renderers/status-glyphs.ts": {
      "bytes": 5000,
      "imports": [
      ],
      "format": "esm"
    },
    "node_modules/zod/v4/classic/external.js": {
      "bytes": 907,
      "imports": [
        {
          "path": "/Users/nolarose/Projects/scanner/node_modules/zod/v4/core/index.js",
          "kind": "import-statement",
          "original": "../core/index.js"
        },
        {
          "path": "/Users/nolarose/Projects/scanner/node_modules/zod/v4/classic/schemas.js",
          "kind": "import-statement",
          "original": "./schemas.js"
        },
        {
          "path": "/Users/nolarose/Projects/scanner/node_modules/zod/v4/classic/checks.js",
          "kind": "import-statement",
          "original": "./checks.js"
        },
        {
          "path": "/Users/nolarose/Projects/scanner/node_modules/zod/v4/classic/errors.js",
          "kind": "import-statement",
          "original": "./errors.js"
        },
        {
          "path": "/Users/nolarose/Projects/scanner/node_modules/zod/v4/classic/parse.js",
          "kind": "import-statement",
          "original": "./parse.js"
        },
        {
          "path": "/Users/nolarose/Projects/scanner/node_modules/zod/v4/classic/compat.js",
          "kind": "import-statement",
          "original": "./compat.js"
        },
        {
          "path": "/Users/nolarose/Projects/scanner/node_modules/zod/v4/core/index.js",
          "kind": "import-statement",
          "original": "../core/index.js"
        },
        {
          "path": "/Users/nolarose/Projects/scanner/node_modules/zod/v4/locales/en.js",
          "kind": "import-statement",
          "original": "../locales/en.js"
        },
        {
          "path": "/Users/nolarose/Projects/scanner/node_modules/zod/v4/core/index.js",
          "kind": "import-statement",
          "original": "../core/index.js"
        },
        {
          "path": "/Users/nolarose/Projects/scanner/node_modules/zod/v4/core/json-schema-processors.js",
          "kind": "import-statement",
          "original": "../core/json-schema-processors.js"
        },
        {
          "path": "/Users/nolarose/Projects/scanner/node_modules/zod/v4/classic/from-json-schema.js",
          "kind": "import-statement",
          "original": "./from-json-schema.js"
        },
        {
          "path": "/Users/nolarose/Projects/scanner/node_modules/zod/v4/locales/index.js",
          "kind": "import-statement",
          "original": "../locales/index.js"
        },
        {
          "path": "/Users/nolarose/Projects/scanner/node_modules/zod/v4/classic/iso.js",
          "kind": "import-statement",
          "original": "./iso.js"
        },
        {
          "path": "/Users/nolarose/Projects/scanner/node_modules/zod/v4/classic/iso.js",
          "kind": "import-statement",
          "original": "./iso.js"
        },
        {
          "path": "/Users/nolarose/Projects/scanner/node_modules/zod/v4/classic/coerce.js",
          "kind": "import-statement",
          "original": "./coerce.js"
        }
      ],
      "format": "esm"
    },
    "node_modules/zod/v4/core/index.js": {
      "bytes": 594,
      "imports": [
        {
          "path": "/Users/nolarose/Projects/scanner/node_modules/zod/v4/core/core.js",
          "kind": "import-statement",
          "original": "./core.js"
        },
        {
          "path": "/Users/nolarose/Projects/scanner/node_modules/zod/v4/core/parse.js",
          "kind": "import-statement",
          "original": "./parse.js"
        },
        {
          "path": "/Users/nolarose/Projects/scanner/node_modules/zod/v4/core/errors.js",
          "kind": "import-statement",
          "original": "./errors.js"
        },
        {
          "path": "/Users/nolarose/Projects/scanner/node_modules/zod/v4/core/schemas.js",
          "kind": "import-statement",
          "original": "./schemas.js"
        },
        {
          "path": "/Users/nolarose/Projects/scanner/node_modules/zod/v4/core/checks.js",
          "kind": "import-statement",
          "original": "./checks.js"
        },
        {
          "path": "/Users/nolarose/Projects/scanner/node_modules/zod/v4/core/versions.js",
          "kind": "import-statement",
          "original": "./versions.js"
        },
        {
          "path": "/Users/nolarose/Projects/scanner/node_modules/zod/v4/core/util.js",
          "kind": "import-statement",
          "original": "./util.js"
        },
        {
          "path": "/Users/nolarose/Projects/scanner/node_modules/zod/v4/core/regexes.js",
          "kind": "import-statement",
          "original": "./regexes.js"
        },
        {
          "path": "../locales/index.js",
          "kind": "import-statement"
        },
        {
          "path": "/Users/nolarose/Projects/scanner/node_modules/zod/v4/core/registries.js",
          "kind": "import-statement",
          "original": "./registries.js"
        },
        {
          "path": "/Users/nolarose/Projects/scanner/node_modules/zod/v4/core/doc.js",
          "kind": "import-statement",
          "original": "./doc.js"
        },
        {
          "path": "/Users/nolarose/Projects/scanner/node_modules/zod/v4/core/api.js",
          "kind": "import-statement",
          "original": "./api.js"
        },
        {
          "path": "/Users/nolarose/Projects/scanner/node_modules/zod/v4/core/to-json-schema.js",
          "kind": "import-statement",
          "original": "./to-json-schema.js"
        },
        {
          "path": "./json-schema-processors.js",
          "kind": "import-statement"
        },
        {
          "path": "/Users/nolarose/Projects/scanner/node_modules/zod/v4/core/json-schema-generator.js",
          "kind": "import-statement",
          "original": "./json-schema-generator.js"
        },
        {
          "path": "/Users/nolarose/Projects/scanner/node_modules/zod/v4/core/json-schema.js",
          "kind": "import-statement",
          "original": "./json-schema.js"
        }
      ],
      "format": "esm"
    },
    "node_modules/zod/v4/classic/errors.js": {
      "bytes": 1581,
      "imports": [
        {
          "path": "../core/index.js",
          "kind": "import-statement"
        },
        {
          "path": "../core/index.js",
          "kind": "import-statement"
        },
        {
          "path": "../core/util.js",
          "kind": "import-statement"
        }
      ],
      "format": "esm"
    },
    "node_modules/zod/v4/core/json-schema-processors.js": {
      "bytes": 20882,
      "imports": [
        {
          "path": "./to-json-schema.js",
          "kind": "import-statement"
        },
        {
          "path": "./util.js",
          "kind": "import-statement"
        }
      ],
      "format": "esm"
    },
    "node_modules/zod/v4/classic/checks.js": {
      "bytes": 663,
      "imports": [
        {
          "path": "../core/index.js",
          "kind": "import-statement"
        }
      ],
      "format": "esm"
    },
    "node_modules/zod/v4/classic/schemas.js": {
      "bytes": 45601,
      "imports": [
        {
          "path": "../core/index.js",
          "kind": "import-statement"
        },
        {
          "path": "../core/index.js",
          "kind": "import-statement"
        },
        {
          "path": "../core/json-schema-processors.js",
          "kind": "import-statement"
        },
        {
          "path": "../core/to-json-schema.js",
          "kind": "import-statement"
        },
        {
          "path": "./checks.js",
          "kind": "import-statement"
        },
        {
          "path": "./iso.js",
          "kind": "import-statement"
        },
        {
          "path": "./parse.js",
          "kind": "import-statement"
        }
      ],
      "format": "esm"
    },
    "node_modules/zod/v4/classic/from-json-schema.js": {
      "bytes": 23172,
      "imports": [
        {
          "path": "../core/registries.js",
          "kind": "import-statement"
        },
        {
          "path": "./checks.js",
          "kind": "import-statement"
        },
        {
          "path": "./iso.js",
          "kind": "import-statement"
        },
        {
          "path": "./schemas.js",
          "kind": "import-statement"
        }
      ],
      "format": "esm"
    },
    "node_modules/zod/v4/classic/compat.js": {
      "bytes": 1090,
      "imports": [
        {
          "path": "../core/index.js",
          "kind": "import-statement"
        },
        {
          "path": "../core/index.js",
          "kind": "import-statement"
        }
      ],
      "format": "esm"
    },
    "node_modules/zod/v4/locales/en.js": {
      "bytes": 4533,
      "imports": [
        {
          "path": "../core/util.js",
          "kind": "import-statement"
        }
      ],
      "format": "esm"
    },
    "node_modules/zod/v4/classic/iso.js": {
      "bytes": 1151,
      "imports": [
        {
          "path": "../core/index.js",
          "kind": "import-statement"
        },
        {
          "path": "./schemas.js",
          "kind": "import-statement"
        }
      ],
      "format": "esm"
    },
    "node_modules/zod/v4/classic/coerce.js": {
      "bytes": 550,
      "imports": [
        {
          "path": "../core/index.js",
          "kind": "import-statement"
        },
        {
          "path": "./schemas.js",
          "kind": "import-statement"
        }
      ],
      "format": "esm"
    },
    "node_modules/zod/v4/classic/parse.js": {
      "bytes": 997,
      "imports": [
        {
          "path": "../core/index.js",
          "kind": "import-statement"
        },
        {
          "path": "./errors.js",
          "kind": "import-statement"
        }
      ],
      "format": "esm"
    },
    "node_modules/zod/v4/locales/index.js": {
      "bytes": 2026,
      "imports": [
        {
          "path": "/Users/nolarose/Projects/scanner/node_modules/zod/v4/locales/ar.js",
          "kind": "import-statement",
          "original": "./ar.js"
        },
        {
          "path": "/Users/nolarose/Projects/scanner/node_modules/zod/v4/locales/az.js",
          "kind": "import-statement",
          "original": "./az.js"
        },
        {
          "path": "/Users/nolarose/Projects/scanner/node_modules/zod/v4/locales/be.js",
          "kind": "import-statement",
          "original": "./be.js"
        },
        {
          "path": "/Users/nolarose/Projects/scanner/node_modules/zod/v4/locales/bg.js",
          "kind": "import-statement",
          "original": "./bg.js"
        },
        {
          "path": "/Users/nolarose/Projects/scanner/node_modules/zod/v4/locales/ca.js",
          "kind": "import-statement",
          "original": "./ca.js"
        },
        {
          "path": "/Users/nolarose/Projects/scanner/node_modules/zod/v4/locales/cs.js",
          "kind": "import-statement",
          "original": "./cs.js"
        },
        {
          "path": "/Users/nolarose/Projects/scanner/node_modules/zod/v4/locales/da.js",
          "kind": "import-statement",
          "original": "./da.js"
        },
        {
          "path": "/Users/nolarose/Projects/scanner/node_modules/zod/v4/locales/de.js",
          "kind": "import-statement",
          "original": "./de.js"
        },
        {
          "path": "./en.js",
          "kind": "import-statement"
        },
        {
          "path": "/Users/nolarose/Projects/scanner/node_modules/zod/v4/locales/eo.js",
          "kind": "import-statement",
          "original": "./eo.js"
        },
        {
          "path": "/Users/nolarose/Projects/scanner/node_modules/zod/v4/locales/es.js",
          "kind": "import-statement",
          "original": "./es.js"
        },
        {
          "path": "/Users/nolarose/Projects/scanner/node_modules/zod/v4/locales/fa.js",
          "kind": "import-statement",
          "original": "./fa.js"
        },
        {
          "path": "/Users/nolarose/Projects/scanner/node_modules/zod/v4/locales/fi.js",
          "kind": "import-statement",
          "original": "./fi.js"
        },
        {
          "path": "/Users/nolarose/Projects/scanner/node_modules/zod/v4/locales/fr.js",
          "kind": "import-statement",
          "original": "./fr.js"
        },
        {
          "path": "/Users/nolarose/Projects/scanner/node_modules/zod/v4/locales/fr-CA.js",
          "kind": "import-statement",
          "original": "./fr-CA.js"
        },
        {
          "path": "/Users/nolarose/Projects/scanner/node_modules/zod/v4/locales/he.js",
          "kind": "import-statement",
          "original": "./he.js"
        },
        {
          "path": "/Users/nolarose/Projects/scanner/node_modules/zod/v4/locales/hu.js",
          "kind": "import-statement",
          "original": "./hu.js"
        },
        {
          "path": "/Users/nolarose/Projects/scanner/node_modules/zod/v4/locales/hy.js",
          "kind": "import-statement",
          "original": "./hy.js"
        },
        {
          "path": "/Users/nolarose/Projects/scanner/node_modules/zod/v4/locales/id.js",
          "kind": "import-statement",
          "original": "./id.js"
        },
        {
          "path": "/Users/nolarose/Projects/scanner/node_modules/zod/v4/locales/is.js",
          "kind": "import-statement",
          "original": "./is.js"
        },
        {
          "path": "/Users/nolarose/Projects/scanner/node_modules/zod/v4/locales/it.js",
          "kind": "import-statement",
          "original": "./it.js"
        },
        {
          "path": "/Users/nolarose/Projects/scanner/node_modules/zod/v4/locales/ja.js",
          "kind": "import-statement",
          "original": "./ja.js"
        },
        {
          "path": "/Users/nolarose/Projects/scanner/node_modules/zod/v4/locales/ka.js",
          "kind": "import-statement",
          "original": "./ka.js"
        },
        {
          "path": "/Users/nolarose/Projects/scanner/node_modules/zod/v4/locales/kh.js",
          "kind": "import-statement",
          "original": "./kh.js"
        },
        {
          "path": "/Users/nolarose/Projects/scanner/node_modules/zod/v4/locales/km.js",
          "kind": "import-statement",
          "original": "./km.js"
        },
        {
          "path": "/Users/nolarose/Projects/scanner/node_modules/zod/v4/locales/ko.js",
          "kind": "import-statement",
          "original": "./ko.js"
        },
        {
          "path": "/Users/nolarose/Projects/scanner/node_modules/zod/v4/locales/lt.js",
          "kind": "import-statement",
          "original": "./lt.js"
        },
        {
          "path": "/Users/nolarose/Projects/scanner/node_modules/zod/v4/locales/mk.js",
          "kind": "import-statement",
          "original": "./mk.js"
        },
        {
          "path": "/Users/nolarose/Projects/scanner/node_modules/zod/v4/locales/ms.js",
          "kind": "import-statement",
          "original": "./ms.js"
        },
        {
          "path": "/Users/nolarose/Projects/scanner/node_modules/zod/v4/locales/nl.js",
          "kind": "import-statement",
          "original": "./nl.js"
        },
        {
          "path": "/Users/nolarose/Projects/scanner/node_modules/zod/v4/locales/no.js",
          "kind": "import-statement",
          "original": "./no.js"
        },
        {
          "path": "/Users/nolarose/Projects/scanner/node_modules/zod/v4/locales/ota.js",
          "kind": "import-statement",
          "original": "./ota.js"
        },
        {
          "path": "/Users/nolarose/Projects/scanner/node_modules/zod/v4/locales/ps.js",
          "kind": "import-statement",
          "original": "./ps.js"
        },
        {
          "path": "/Users/nolarose/Projects/scanner/node_modules/zod/v4/locales/pl.js",
          "kind": "import-statement",
          "original": "./pl.js"
        },
        {
          "path": "/Users/nolarose/Projects/scanner/node_modules/zod/v4/locales/pt.js",
          "kind": "import-statement",
          "original": "./pt.js"
        },
        {
          "path": "/Users/nolarose/Projects/scanner/node_modules/zod/v4/locales/ru.js",
          "kind": "import-statement",
          "original": "./ru.js"
        },
        {
          "path": "/Users/nolarose/Projects/scanner/node_modules/zod/v4/locales/sl.js",
          "kind": "import-statement",
          "original": "./sl.js"
        },
        {
          "path": "/Users/nolarose/Projects/scanner/node_modules/zod/v4/locales/sv.js",
          "kind": "import-statement",
          "original": "./sv.js"
        },
        {
          "path": "/Users/nolarose/Projects/scanner/node_modules/zod/v4/locales/ta.js",
          "kind": "import-statement",
          "original": "./ta.js"
        },
        {
          "path": "/Users/nolarose/Projects/scanner/node_modules/zod/v4/locales/th.js",
          "kind": "import-statement",
          "original": "./th.js"
        },
        {
          "path": "/Users/nolarose/Projects/scanner/node_modules/zod/v4/locales/tr.js",
          "kind": "import-statement",
          "original": "./tr.js"
        },
        {
          "path": "/Users/nolarose/Projects/scanner/node_modules/zod/v4/locales/ua.js",
          "kind": "import-statement",
          "original": "./ua.js"
        },
        {
          "path": "/Users/nolarose/Projects/scanner/node_modules/zod/v4/locales/uk.js",
          "kind": "import-statement",
          "original": "./uk.js"
        },
        {
          "path": "/Users/nolarose/Projects/scanner/node_modules/zod/v4/locales/ur.js",
          "kind": "import-statement",
          "original": "./ur.js"
        },
        {
          "path": "/Users/nolarose/Projects/scanner/node_modules/zod/v4/locales/uz.js",
          "kind": "import-statement",
          "original": "./uz.js"
        },
        {
          "path": "/Users/nolarose/Projects/scanner/node_modules/zod/v4/locales/vi.js",
          "kind": "import-statement",
          "original": "./vi.js"
        },
        {
          "path": "/Users/nolarose/Projects/scanner/node_modules/zod/v4/locales/zh-CN.js",
          "kind": "import-statement",
          "original": "./zh-CN.js"
        },
        {
          "path": "/Users/nolarose/Projects/scanner/node_modules/zod/v4/locales/zh-TW.js",
          "kind": "import-statement",
          "original": "./zh-TW.js"
        },
        {
          "path": "/Users/nolarose/Projects/scanner/node_modules/zod/v4/locales/yo.js",
          "kind": "import-statement",
          "original": "./yo.js"
        }
      ],
      "format": "esm"
    },
    "node_modules/zod/v4/core/registries.js": {
      "bytes": 1512,
      "imports": [
      ],
      "format": "esm"
    },
    "node_modules/zod/v4/core/util.js": {
      "bytes": 21335,
      "imports": [
      ],
      "format": "esm"
    },
    "node_modules/zod/v4/core/core.js": {
      "bytes": 2459,
      "imports": [
      ],
      "format": "esm"
    },
    "node_modules/zod/v4/core/parse.js": {
      "bytes": 4528,
      "imports": [
        {
          "path": "./core.js",
          "kind": "import-statement"
        },
        {
          "path": "./errors.js",
          "kind": "import-statement"
        },
        {
          "path": "./util.js",
          "kind": "import-statement"
        }
      ],
      "format": "esm"
    },
    "node_modules/zod/v4/core/versions.js": {
      "bytes": 70,
      "imports": [
      ],
      "format": "esm"
    },
    "node_modules/zod/v4/core/checks.js": {
      "bytes": 20005,
      "imports": [
        {
          "path": "./core.js",
          "kind": "import-statement"
        },
        {
          "path": "./regexes.js",
          "kind": "import-statement"
        },
        {
          "path": "./util.js",
          "kind": "import-statement"
        }
      ],
      "format": "esm"
    },
    "node_modules/zod/v4/core/regexes.js": {
      "bytes": 8840,
      "imports": [
        {
          "path": "./util.js",
          "kind": "import-statement"
        }
      ],
      "format": "esm"
    },
    "node_modules/zod/v4/core/json-schema-generator.js": {
      "bytes": 3218,
      "imports": [
        {
          "path": "./json-schema-processors.js",
          "kind": "import-statement"
        },
        {
          "path": "./to-json-schema.js",
          "kind": "import-statement"
        }
      ],
      "format": "esm"
    },
    "node_modules/zod/v4/core/errors.js": {
      "bytes": 6123,
      "imports": [
        {
          "path": "./core.js",
          "kind": "import-statement"
        },
        {
          "path": "./util.js",
          "kind": "import-statement"
        }
      ],
      "format": "esm"
    },
    "node_modules/zod/v4/core/json-schema.js": {
      "bytes": 11,
      "imports": [
      ],
      "format": "esm"
    },
    "node_modules/zod/v4/core/doc.js": {
      "bytes": 1088,
      "imports": [
      ],
      "format": "esm"
    },
    "node_modules/zod/v4/core/to-json-schema.js": {
      "bytes": 16397,
      "imports": [
        {
          "path": "./registries.js",
          "kind": "import-statement"
        }
      ],
      "format": "esm"
    },
    "node_modules/zod/v4/core/api.js": {
      "bytes": 27841,
      "imports": [
        {
          "path": "./checks.js",
          "kind": "import-statement"
        },
        {
          "path": "./registries.js",
          "kind": "import-statement"
        },
        {
          "path": "./schemas.js",
          "kind": "import-statement"
        },
        {
          "path": "./util.js",
          "kind": "import-statement"
        }
      ],
      "format": "esm"
    },
    "node_modules/zod/v4/core/schemas.js": {
      "bytes": 76984,
      "imports": [
        {
          "path": "./checks.js",
          "kind": "import-statement"
        },
        {
          "path": "./core.js",
          "kind": "import-statement"
        },
        {
          "path": "./doc.js",
          "kind": "import-statement"
        },
        {
          "path": "./parse.js",
          "kind": "import-statement"
        },
        {
          "path": "./regexes.js",
          "kind": "import-statement"
        },
        {
          "path": "./util.js",
          "kind": "import-statement"
        },
        {
          "path": "./versions.js",
          "kind": "import-statement"
        },
        {
          "path": "./util.js",
          "kind": "import-statement"
        }
      ],
      "format": "esm"
    },
    "node_modules/zod/v4/locales/it.js": {
      "bytes": 4572,
      "imports": [
        {
          "path": "../core/util.js",
          "kind": "import-statement"
        }
      ],
      "format": "esm"
    },
    "node_modules/zod/v4/locales/nl.js": {
      "bytes": 4762,
      "imports": [
        {
          "path": "../core/util.js",
          "kind": "import-statement"
        }
      ],
      "format": "esm"
    },
    "node_modules/zod/v4/locales/he.js": {
      "bytes": 12005,
      "imports": [
        {
          "path": "../core/util.js",
          "kind": "import-statement"
        }
      ],
      "format": "esm"
    },
    "node_modules/zod/v4/locales/no.js": {
      "bytes": 4506,
      "imports": [
        {
          "path": "../core/util.js",
          "kind": "import-statement"
        }
      ],
      "format": "esm"
    },
    "node_modules/zod/v4/locales/pl.js": {
      "bytes": 4966,
      "imports": [
        {
          "path": "../core/util.js",
          "kind": "import-statement"
        }
      ],
      "format": "esm"
    },
    "node_modules/zod/v4/locales/sl.js": {
      "bytes": 4567,
      "imports": [
        {
          "path": "../core/util.js",
          "kind": "import-statement"
        }
      ],
      "format": "esm"
    },
    "node_modules/zod/v4/locales/th.js": {
      "bytes": 6290,
      "imports": [
        {
          "path": "../core/util.js",
          "kind": "import-statement"
        }
      ],
      "format": "esm"
    },
    "node_modules/zod/v4/locales/hu.js": {
      "bytes": 4696,
      "imports": [
        {
          "path": "../core/util.js",
          "kind": "import-statement"
        }
      ],
      "format": "esm"
    },
    "node_modules/zod/v4/locales/uk.js": {
      "bytes": 5430,
      "imports": [
        {
          "path": "../core/util.js",
          "kind": "import-statement"
        }
      ],
      "format": "esm"
    },
    "node_modules/zod/v4/locales/lt.js": {
      "bytes": 8082,
      "imports": [
        {
          "path": "../core/util.js",
          "kind": "import-statement"
        }
      ],
      "format": "esm"
    },
    "node_modules/zod/v4/locales/ur.js": {
      "bytes": 5271,
      "imports": [
        {
          "path": "../core/util.js",
          "kind": "import-statement"
        }
      ],
      "format": "esm"
    },
    "node_modules/zod/v4/locales/id.js": {
      "bytes": 4577,
      "imports": [
        {
          "path": "../core/util.js",
          "kind": "import-statement"
        }
      ],
      "format": "esm"
    },
    "node_modules/zod/v4/locales/az.js": {
      "bytes": 4511,
      "imports": [
        {
          "path": "../core/util.js",
          "kind": "import-statement"
        }
      ],
      "format": "esm"
    },
    "node_modules/zod/v4/locales/mk.js": {
      "bytes": 5157,
      "imports": [
        {
          "path": "../core/util.js",
          "kind": "import-statement"
        }
      ],
      "format": "esm"
    },
    "node_modules/zod/v4/locales/zh-TW.js": {
      "bytes": 4498,
      "imports": [
        {
          "path": "../core/util.js",
          "kind": "import-statement"
        }
      ],
      "format": "esm"
    },
    "node_modules/zod/v4/locales/pt.js": {
      "bytes": 4568,
      "imports": [
        {
          "path": "../core/util.js",
          "kind": "import-statement"
        }
      ],
      "format": "esm"
    },
    "node_modules/zod/v4/locales/zh-CN.js": {
      "bytes": 4452,
      "imports": [
        {
          "path": "../core/util.js",
          "kind": "import-statement"
        }
      ],
      "format": "esm"
    },
    "node_modules/zod/v4/locales/ru.js": {
      "bytes": 6714,
      "imports": [
        {
          "path": "../core/util.js",
          "kind": "import-statement"
        }
      ],
      "format": "esm"
    },
    "node_modules/zod/v4/locales/da.js": {
      "bytes": 4804,
      "imports": [
        {
          "path": "../core/util.js",
          "kind": "import-statement"
        }
      ],
      "format": "esm"
    },
    "node_modules/zod/v4/locales/fi.js": {
      "bytes": 4818,
      "imports": [
        {
          "path": "../core/util.js",
          "kind": "import-statement"
        }
      ],
      "format": "esm"
    },
    "node_modules/zod/v4/locales/ota.js": {
      "bytes": 4525,
      "imports": [
        {
          "path": "../core/util.js",
          "kind": "import-statement"
        }
      ],
      "format": "esm"
    },
    "node_modules/zod/v4/locales/ms.js": {
      "bytes": 4491,
      "imports": [
        {
          "path": "../core/util.js",
          "kind": "import-statement"
        }
      ],
      "format": "esm"
    },
    "node_modules/zod/v4/locales/fa.js": {
      "bytes": 5131,
      "imports": [
        {
          "path": "../core/util.js",
          "kind": "import-statement"
        }
      ],
      "format": "esm"
    },
    "node_modules/zod/v4/locales/tr.js": {
      "bytes": 4454,
      "imports": [
        {
          "path": "../core/util.js",
          "kind": "import-statement"
        }
      ],
      "format": "esm"
    },
    "node_modules/zod/v4/locales/kh.js": {
      "bytes": 111,
      "imports": [
        {
          "path": "./km.js",
          "kind": "import-statement"
        }
      ],
      "format": "esm"
    },
    "node_modules/zod/v4/locales/uz.js": {
      "bytes": 4681,
      "imports": [
        {
          "path": "../core/util.js",
          "kind": "import-statement"
        }
      ],
      "format": "esm"
    },
    "node_modules/zod/v4/locales/be.js": {
      "bytes": 6619,
      "imports": [
        {
          "path": "../core/util.js",
          "kind": "import-statement"
        }
      ],
      "format": "esm"
    },
    "node_modules/zod/v4/locales/bg.js": {
      "bytes": 5785,
      "imports": [
        {
          "path": "../core/util.js",
          "kind": "import-statement"
        }
      ],
      "format": "esm"
    },
    "node_modules/zod/v4/locales/es.js": {
      "bytes": 5439,
      "imports": [
        {
          "path": "../core/util.js",
          "kind": "import-statement"
        }
      ],
      "format": "esm"
    },
    "node_modules/zod/v4/locales/sv.js": {
      "bytes": 4663,
      "imports": [
        {
          "path": "../core/util.js",
          "kind": "import-statement"
        }
      ],
      "format": "esm"
    },
    "node_modules/zod/v4/locales/eo.js": {
      "bytes": 4603,
      "imports": [
        {
          "path": "../core/util.js",
          "kind": "import-statement"
        }
      ],
      "format": "esm"
    },
    "node_modules/zod/v4/locales/yo.js": {
      "bytes": 4665,
      "imports": [
        {
          "path": "../core/util.js",
          "kind": "import-statement"
        }
      ],
      "format": "esm"
    },
    "node_modules/zod/v4/locales/ja.js": {
      "bytes": 4851,
      "imports": [
        {
          "path": "../core/util.js",
          "kind": "import-statement"
        }
      ],
      "format": "esm"
    },
    "node_modules/zod/v4/locales/ko.js": {
      "bytes": 4929,
      "imports": [
        {
          "path": "../core/util.js",
          "kind": "import-statement"
        }
      ],
      "format": "esm"
    },
    "node_modules/zod/v4/locales/vi.js": {
      "bytes": 4772,
      "imports": [
        {
          "path": "../core/util.js",
          "kind": "import-statement"
        }
      ],
      "format": "esm"
    },
    "node_modules/zod/v4/locales/fr-CA.js": {
      "bytes": 4554,
      "imports": [
        {
          "path": "../core/util.js",
          "kind": "import-statement"
        }
      ],
      "format": "esm"
    },
    "node_modules/zod/v4/locales/ar.js": {
      "bytes": 5188,
      "imports": [
        {
          "path": "../core/util.js",
          "kind": "import-statement"
        }
      ],
      "format": "esm"
    },
    "node_modules/zod/v4/locales/ka.js": {
      "bytes": 6274,
      "imports": [
        {
          "path": "../core/util.js",
          "kind": "import-statement"
        }
      ],
      "format": "esm"
    },
    "node_modules/zod/v4/locales/fr.js": {
      "bytes": 4585,
      "imports": [
        {
          "path": "../core/util.js",
          "kind": "import-statement"
        }
      ],
      "format": "esm"
    },
    "node_modules/zod/v4/locales/ca.js": {
      "bytes": 4710,
      "imports": [
        {
          "path": "../core/util.js",
          "kind": "import-statement"
        }
      ],
      "format": "esm"
    },
    "node_modules/zod/v4/locales/is.js": {
      "bytes": 4635,
      "imports": [
        {
          "path": "../core/util.js",
          "kind": "import-statement"
        }
      ],
      "format": "esm"
    },
    "node_modules/zod/v4/locales/de.js": {
      "bytes": 4588,
      "imports": [
        {
          "path": "../core/util.js",
          "kind": "import-statement"
        }
      ],
      "format": "esm"
    },
    "node_modules/zod/v4/locales/km.js": {
      "bytes": 6242,
      "imports": [
        {
          "path": "../core/util.js",
          "kind": "import-statement"
        }
      ],
      "format": "esm"
    },
    "node_modules/zod/v4/locales/ps.js": {
      "bytes": 4909,
      "imports": [
        {
          "path": "../core/util.js",
          "kind": "import-statement"
        }
      ],
      "format": "esm"
    },
    "node_modules/zod/v4/locales/ta.js": {
      "bytes": 6369,
      "imports": [
        {
          "path": "../core/util.js",
          "kind": "import-statement"
        }
      ],
      "format": "esm"
    },
    "node_modules/zod/v4/locales/ua.js": {
      "bytes": 111,
      "imports": [
        {
          "path": "./uk.js",
          "kind": "import-statement"
        }
      ],
      "format": "esm"
    },
    "node_modules/zod/v4/locales/hy.js": {
      "bytes": 6390,
      "imports": [
        {
          "path": "../core/util.js",
          "kind": "import-statement"
        }
      ],
      "format": "esm"
    },
    "node_modules/zod/v4/locales/cs.js": {
      "bytes": 4772,
      "imports": [
        {
          "path": "../core/util.js",
          "kind": "import-statement"
        }
      ],
      "format": "esm"
    }
  },
  "outputs": {
    "./scan.js": {
      "bytes": 679760,
      "inputs": {
        "node_modules/zod/v4/core/core.js": {
          "bytesInOutput": 1882
        },
        "node_modules/zod/v4/core/util.js": {
          "bytesInOutput": 19505
        },
        "node_modules/zod/v4/core/errors.js": {
          "bytesInOutput": 4413
        },
        "node_modules/zod/v4/core/parse.js": {
          "bytesInOutput": 3874
        },
        "node_modules/zod/v4/core/regexes.js": {
          "bytesInOutput": 7448
        },
        "node_modules/zod/v4/core/checks.js": {
          "bytesInOutput": 16218
        },
        "node_modules/zod/v4/core/doc.js": {
          "bytesInOutput": 915
        },
        "node_modules/zod/v4/core/versions.js": {
          "bytesInOutput": 54
        },
        "node_modules/zod/v4/core/schemas.js": {
          "bytesInOutput": 61590
        },
        "node_modules/zod/v4/locales/ar.js": {
          "bytesInOutput": 4573
        },
        "node_modules/zod/v4/locales/az.js": {
          "bytesInOutput": 3904
        },
        "node_modules/zod/v4/locales/be.js": {
          "bytesInOutput": 5726
        },
        "node_modules/zod/v4/locales/bg.js": {
          "bytesInOutput": 5057
        },
        "node_modules/zod/v4/locales/ca.js": {
          "bytesInOutput": 4006
        },
        "node_modules/zod/v4/locales/cs.js": {
          "bytesInOutput": 4132
        },
        "node_modules/zod/v4/locales/da.js": {
          "bytesInOutput": 4145
        },
        "node_modules/zod/v4/locales/de.js": {
          "bytesInOutput": 3965
        },
        "node_modules/zod/v4/locales/en.js": {
          "bytesInOutput": 3703
        },
        "node_modules/zod/v4/locales/eo.js": {
          "bytesInOutput": 3979
        },
        "node_modules/zod/v4/locales/es.js": {
          "bytesInOutput": 4717
        },
        "node_modules/zod/v4/locales/fa.js": {
          "bytesInOutput": 4462
        },
        "node_modules/zod/v4/locales/fi.js": {
          "bytesInOutput": 4167
        },
        "node_modules/zod/v4/locales/fr.js": {
          "bytesInOutput": 3965
        },
        "node_modules/zod/v4/locales/fr-CA.js": {
          "bytesInOutput": 3937
        },
        "node_modules/zod/v4/locales/he.js": {
          "bytesInOutput": 9684
        },
        "node_modules/zod/v4/locales/hu.js": {
          "bytesInOutput": 4075
        },
        "node_modules/zod/v4/locales/hy.js": {
          "bytesInOutput": 5549
        },
        "node_modules/zod/v4/locales/id.js": {
          "bytesInOutput": 3964
        },
        "node_modules/zod/v4/locales/is.js": {
          "bytesInOutput": 4006
        },
        "node_modules/zod/v4/locales/it.js": {
          "bytesInOutput": 3952
        },
        "node_modules/zod/v4/locales/ja.js": {
          "bytesInOutput": 4238
        },
        "node_modules/zod/v4/locales/ka.js": {
          "bytesInOutput": 5633
        },
        "node_modules/zod/v4/locales/km.js": {
          "bytesInOutput": 5608
        },
        "node_modules/zod/v4/locales/kh.js": {
          "bytesInOutput": 49
        },
        "node_modules/zod/v4/locales/ko.js": {
          "bytesInOutput": 4275
        },
        "node_modules/zod/v4/locales/lt.js": {
          "bytesInOutput": 6838
        },
        "node_modules/zod/v4/locales/mk.js": {
          "bytesInOutput": 4528
        },
        "node_modules/zod/v4/locales/ms.js": {
          "bytesInOutput": 3873
        },
        "node_modules/zod/v4/locales/nl.js": {
          "bytesInOutput": 4125
        },
        "node_modules/zod/v4/locales/no.js": {
          "bytesInOutput": 3885
        },
        "node_modules/zod/v4/locales/ota.js": {
          "bytesInOutput": 3901
        },
        "node_modules/zod/v4/locales/ps.js": {
          "bytesInOutput": 4240
        },
        "node_modules/zod/v4/locales/pl.js": {
          "bytesInOutput": 4337
        },
        "node_modules/zod/v4/locales/pt.js": {
          "bytesInOutput": 3948
        },
        "node_modules/zod/v4/locales/ru.js": {
          "bytesInOutput": 5824
        },
        "node_modules/zod/v4/locales/sl.js": {
          "bytesInOutput": 3938
        },
        "node_modules/zod/v4/locales/sv.js": {
          "bytesInOutput": 4026
        },
        "node_modules/zod/v4/locales/ta.js": {
          "bytesInOutput": 5733
        },
        "node_modules/zod/v4/locales/th.js": {
          "bytesInOutput": 5656
        },
        "node_modules/zod/v4/locales/tr.js": {
          "bytesInOutput": 3849
        },
        "node_modules/zod/v4/locales/uk.js": {
          "bytesInOutput": 4809
        },
        "node_modules/zod/v4/locales/ua.js": {
          "bytesInOutput": 49
        },
        "node_modules/zod/v4/locales/ur.js": {
          "bytesInOutput": 4638
        },
        "node_modules/zod/v4/locales/uz.js": {
          "bytesInOutput": 4056
        },
        "node_modules/zod/v4/locales/vi.js": {
          "bytesInOutput": 4150
        },
        "node_modules/zod/v4/locales/zh-CN.js": {
          "bytesInOutput": 3829
        },
        "node_modules/zod/v4/locales/zh-TW.js": {
          "bytesInOutput": 3880
        },
        "node_modules/zod/v4/locales/yo.js": {
          "bytesInOutput": 4049
        },
        "node_modules/zod/v4/locales/index.js": {
          "bytesInOutput": 1250
        },
        "node_modules/zod/v4/core/registries.js": {
          "bytesInOutput": 1207
        },
        "node_modules/zod/v4/core/api.js": {
          "bytesInOutput": 19923
        },
        "node_modules/zod/v4/core/to-json-schema.js": {
          "bytesInOutput": 11037
        },
        "node_modules/zod/v4/core/json-schema-processors.js": {
          "bytesInOutput": 16985
        },
        "node_modules/zod/v4/core/json-schema-generator.js": {
          "bytesInOutput": 1594
        },
        "node_modules/zod/v4/core/json-schema.js": {
          "bytesInOutput": 30
        },
        "node_modules/zod/v4/core/index.js": {
          "bytesInOutput": 8826
        },
        "node_modules/zod/v4/classic/checks.js": {
          "bytesInOutput": 858
        },
        "node_modules/zod/v4/classic/iso.js": {
          "bytesInOutput": 1193
        },
        "node_modules/zod/v4/classic/errors.js": {
          "bytesInOutput": 851
        },
        "node_modules/zod/v4/classic/parse.js": {
          "bytesInOutput": 736
        },
        "node_modules/zod/v4/classic/schemas.js": {
          "bytesInOutput": 42393
        },
        "node_modules/zod/v4/classic/compat.js": {
          "bytesInOutput": 624
        },
        "node_modules/zod/v4/classic/from-json-schema.js": {
          "bytesInOutput": 16013
        },
        "node_modules/zod/v4/classic/coerce.js": {
          "bytesInOutput": 540
        },
        "node_modules/zod/v4/classic/external.js": {
          "bytesInOutput": 6836
        },
        "node_modules/zod/index.js": {
          "bytesInOutput": 0
        },
        "src/scan-columns.ts": {
          "bytesInOutput": 5578
        },
        "cli/renderers/status-glyphs.ts": {
          "bytesInOutput": 2668
        },
        "scan.ts": {
          "bytesInOutput": 206862
        }
      },
      "imports": [
      ],
      "exports": [
        "validateTokenValue",
        "validateThreatFeed",
        "tokenValueWarnings",
        "tokenSource",
        "timeSince",
        "shouldWarnMise",
        "semverCompare",
        "semverBumpType",
        "scanProject",
        "platformHelp",
        "parseTzFromEnv",
        "parseRssFeed",
        "parseEnvVar",
        "keychainSet",
        "keychainGet",
        "keychainDelete",
        "isVulnerable",
        "isValidTokenName",
        "isFeatureFlagActive",
        "getGitCommitHashShort",
        "getGitCommitHash",
        "generateRssXml",
        "escapeXml",
        "effectiveLinker",
        "decodeXmlEntities",
        "classifyKeychainError",
        "classifyEnvFlag",
        "XrefSnapshotSchema",
        "XrefEntrySchema",
        "ThreatFeedSchema",
        "ThreatFeedItemSchema",
        "ProjectInfoSchema",
        "PackageJsonSchema",
        "NpmPersonSchema",
        "NpmDistSchema",
        "BunInfoResponseSchema",
        "BUN_TOKEN_AUDIT_RSS_PATH",
        "BUN_SCAN_RESULTS_RSS_PATH",
        "BUN_KEYCHAIN_TOKEN_NAMES",
        "BUN_KEYCHAIN_SERVICE_LEGACY",
        "BUN_KEYCHAIN_SERVICE",
        "BUN_ADVISORY_MATCHES_PATH"
      ],
      "entryPoint": "scan.ts"
    }
  }
}
